Metadata-Version: 1.0
Name: clfparser
Version: 0.1
Summary: Apache Common/Combined Log Format Parser
Home-page: http://github.com/nnon/commonlogformat.git
Author: Rob Mackinnon
Author-email: remackinnon@gmail.com
License: MIT
Platform: UNKNOWN
